{
  "project_id": "20180074",
  "department_code": "05010",
  "department_name": "수자원",
  "project_name": "20180074 남강 하천기본계획 및 하천시설관리대장작성 용역",
  "project_path": "Z:05010_수자원\\20180074 남강 하천기본계획 및 하천시설관리대장작성 용역",
  "documents": {
    "contract": [
      {
        "type": "file",
        "name": "남강 하천기본계획-5차분계약서.pdf",
        "path": "남강 하천기본계획-5차분계약서.pdf",
        "full_path": "Z:05010_수자원\\20180074 남강 하천기본계획 및 하천시설관리대장작성 용역\\1. 과업 계약 및 착수\\1.01 계약\\1.01.03 계약서\\남강 하천기본계획-5차분계약서.pdf",
        "depth": 3,
        "doc_type": "contract"
      },
      {
        "type": "file",
        "name": "남강 하천기본계획-3차분계약서.pdf",
        "path": "남강 하천기본계획-3차분계약서.pdf",
        "full_path": "Z:05010_수자원\\20180074 남강 하천기본계획 및 하천시설관리대장작성 용역\\1. 과업 계약 및 착수\\1.01 계약\\1.01.03 계약서\\남강 하천기본계획-3차분계약서.pdf",
        "depth": 3,
        "doc_type": "contract"
      },
      {
        "type": "file",
        "name": "남강 하천기본계획 및 하천시설관리대장 작성 용역(7차) 계약서.pdf",
        "path": "남강 하천기본계획 및 하천시설관리대장 작성 용역(7차) 계약서.pdf",
        "full_path": "Z:05010_수자원\\20180074 남강 하천기본계획 및 하천시설관리대장작성 용역\\1. 과업 계약 및 착수\\1.01 계약\\1.01.03 계약서\\남강 하천기본계획 및 하천시설관리대장 작성 용역(7차) 계약서.pdf",
        "depth": 3,
        "doc_type": "contract"
      }
    ],
    "specification": [
      {
        "type": "file",
        "name": "20180532649-00_1527215171071_(과업지시서)남강 하천기본계획.hwp",
        "path": "20180532649-00_1527215171071_(과업지시서)남강 하천기본계획.hwp",
        "full_path": "Z:05010_수자원\\20180074 남강 하천기본계획 및 하천시설관리대장작성 용역\\1. 과업 계약 및 착수\\1.01 계약\\1.01.01 과업지시서\\20180532649-00_1527215171071_(과업지시서)남강 하천기본계획.hwp",
        "depth": 3,
        "doc_type": "specification"
      },
      {
        "type": "file",
        "name": "01) 과업지시서(가로).6차분.hwp",
        "path": "01) 과업지시서(가로).6차분.hwp",
        "full_path": "Z:05010_수자원\\20180074 남강 하천기본계획 및 하천시설관리대장작성 용역\\1. 과업 계약 및 착수\\1.02 착수계\\1.02.03 착수계\\6차분 착수계\\수령자료-동부\\01) 과업지시서(가로).6차분.hwp",
        "depth": 5,
        "doc_type": "specification"
      },
      {
        "type": "file",
        "name": "01) 과업지시서(가로).hwp",
        "path": "01) 과업지시서(가로).hwp",
        "full_path": "Z:05010_수자원\\20180074 남강 하천기본계획 및 하천시설관리대장작성 용역\\1. 과업 계약 및 착수\\1.02 착수계\\1.02.03 착수계\\3차분 착수계\\03) 3차분(남강)(내역서)\\01) 과업지시서(가로).hwp",
        "depth": 5,
        "doc_type": "specification"
      }
    ],
    "initiation": [
      {
        "type": "file",
        "name": "착수계(6차분)스캔본-수성.pdf",
        "path": "착수계(6차분)스캔본-수성.pdf",
        "full_path": "Z:05010_수자원\\20180074 남강 하천기본계획 및 하천시설관리대장작성 용역\\1. 과업 계약 및 착수\\1.02 착수계\\1.02.03 착수계\\6차분 착수계\\착수계(6차분)스캔본-수성.pdf",
        "depth": 4,
        "doc_type": "initiation"
      },
      {
        "type": "file",
        "name": "남강 4차분 착수계.pdf",
        "path": "남강 4차분 착수계.pdf",
        "full_path": "Z:05010_수자원\\20180074 남강 하천기본계획 및 하천시설관리대장작성 용역\\1. 과업 계약 및 착수\\1.02 착수계\\1.02.03 착수계\\4차분 착수계\\남강 4차분 착수계.pdf",
        "depth": 4,
        "doc_type": "initiation"
      },
      {
        "type": "file",
        "name": "8차분 재착수계(수성).pdf",
        "path": "8차분 재착수계(수성).pdf",
        "full_path": "Z:05010_수자원\\20180074 남강 하천기본계획 및 하천시설관리대장작성 용역\\1. 과업 계약 및 착수\\1.02 착수계\\1.02.03 착수계\\8차분 착수계(재착수)\\8차분 재착수계(수성).pdf",
        "depth": 4,
        "doc_type": "initiation"
      }
    ],
    "agreement": [
      {
        "type": "file",
        "name": "7-1 공동수행협정서.pdf",
        "path": "7-1 공동수행협정서.pdf",
        "full_path": "Z:05010_수자원\\20180074 남강 하천기본계획 및 하천시설관리대장작성 용역\\1. 과업 계약 및 착수\\1.06 업무분담\\7-1 공동수행협정서.pdf",
        "depth": 2,
        "doc_type": "agreement"
      },
      {
        "type": "file",
        "name": "2018.10.12 남강 하천기본계획 협정서.pdf",
        "path": "2018.10.12 남강 하천기본계획 협정서.pdf",
        "full_path": "Z:05010_수자원\\20180074 남강 하천기본계획 및 하천시설관리대장작성 용역\\1. 과업 계약 및 착수\\1.06 업무분담\\2018.10.12 남강 하천기본계획 협정서.pdf",
        "depth": 2,
        "doc_type": "agreement"
      },
      {
        "type": "file",
        "name": "7-1 공동수행협정서.pdf",
        "path": "7-1 공동수행협정서.pdf",
        "full_path": "Z:05010_수자원\\20180074 남강 하천기본계획 및 하천시설관리대장작성 용역\\1. 과업 계약 및 착수\\1.09 기술지원(외주)\\1.09.01 기술지원계약서\\7-1 공동수행협정서.pdf",
        "depth": 3,
        "doc_type": "agreement"
      }
    ],
    "budget": [
      {
        "type": "file",
        "name": "남강 실행예산서.pdf",
        "path": "남강 실행예산서.pdf",
        "full_path": "Z:05010_수자원\\20180074 남강 하천기본계획 및 하천시설관리대장작성 용역\\1. 과업 계약 및 착수\\1.07 실행\\남강 실행예산서.pdf",
        "depth": 2,
        "doc_type": "budget"
      },
      {
        "type": "file",
        "name": "4-1 실행예산서(변경) 및 사업수행계획서.pdf",
        "path": "4-1 실행예산서(변경) 및 사업수행계획서.pdf",
        "full_path": "Z:05010_수자원\\20180074 남강 하천기본계획 및 하천시설관리대장작성 용역\\1. 과업 계약 및 착수\\1.07 실행\\4-1 실행예산서(변경) 및 사업수행계획서.pdf",
        "depth": 2,
        "doc_type": "budget"
      }
    ],
    "deliverable1": [
      {
        "type": "file",
        "name": "00 보고서목차.hwp",
        "path": "00 보고서목차.hwp",
        "full_path": "Z:05010_수자원\\20180074 남강 하천기본계획 및 하천시설관리대장작성 용역\\2. 설계\\2.02 자료조사 및 검토\\2.02.02 관련계획\\상위계획\\2013년 보고서(남강댐 하류구간)\\00 보고서목차.hwp",
        "depth": 5,
        "doc_type": "deliverable1"
      },
      {
        "type": "file",
        "name": "제5편_하천환경본보고서.pdf",
        "path": "제5편_하천환경본보고서.pdf",
        "full_path": "Z:05010_수자원\\20180074 남강 하천기본계획 및 하천시설관리대장작성 용역\\2. 설계\\2.02 자료조사 및 검토\\2.02.02 관련계획\\상위계획\\수장기보고서\\본보고서\\제5편_하천환경본보고서.pdf",
        "depth": 6,
        "doc_type": "deliverable1"
      },
      {
        "type": "file",
        "name": "제7편_수장기_기후변화_상세보고서.pdf",
        "path": "제7편_수장기_기후변화_상세보고서.pdf",
        "full_path": "Z:05010_수자원\\20180074 남강 하천기본계획 및 하천시설관리대장작성 용역\\2. 설계\\2.02 자료조사 및 검토\\2.02.02 관련계획\\상위계획\\수장기보고서\\본보고서\\제7편_수장기_기후변화_상세보고서.pdf",
        "depth": 6,
        "doc_type": "deliverable1"
      }
    ]
  },
  "timestamp": "2025-03-10 01:46:31",
  "performance": {
    "total_time": 3.1285362243652344,
    "search_time": 3.1095001697540283,
    "document_counts": {
      "contract": 3,
      "specification": 3,
      "initiation": 3,
      "agreement": 3,
      "budget": 2,
      "deliverable1": 3
    }
  }
}