{
  "project_id": "20190224",
  "department_code": "06010",
  "department_name": "환경",
  "project_name": "20190224ㅣ한내~덕곡간(1) 4차로 확포장공사 사후환경영향조사용역",
  "project_path": "Z:06010_환경\\1팀\\02.사후환경영향조사\\20190224ㅣ한내~덕곡간(1) 4차로 확포장공사 사후환경영향조사용역",
  "documents": {
    "contract": [
      {
        "type": "file",
        "name": "20191101_(2019년1차)계약서_한내~덕곡간(1) 4차로 확포장공사 사후환경영향조사용역(2019년분).pdf",
        "path": "20191101_(2019년1차)계약서_한내~덕곡간(1) 4차로 확포장공사 사후환경영향조사용역(2019년분).pdf",
        "full_path": "Z:06010_환경\\1팀\\02.사후환경영향조사\\20190224ㅣ한내~덕곡간(1) 4차로 확포장공사 사후환경영향조사용역\\01 행정\\01 계약서\\2019년1차계약서\\20191101_(2019년1차)계약서_한내~덕곡간(1) 4차로 확포장공사 사후환경영향조사용역(2019년분).pdf",
        "depth": 3,
        "doc_type": "contract"
      },
      {
        "type": "file",
        "name": "20201015_(2019년1차)변경계약서_공문.pdf",
        "path": "20201015_(2019년1차)변경계약서_공문.pdf",
        "full_path": "Z:06010_환경\\1팀\\02.사후환경영향조사\\20190224ㅣ한내~덕곡간(1) 4차로 확포장공사 사후환경영향조사용역\\01 행정\\01 계약서\\2019년1차계약서\\20201015_(2019년1차)변경계약서_공문.pdf",
        "depth": 3,
        "doc_type": "contract"
      },
      {
        "type": "file",
        "name": "20201015_(2019년1차)변경계약서_한내~덕곡간(1) 4차로 확포장공사 사후환경영향조사용역(2019년분).pdf",
        "path": "20201015_(2019년1차)변경계약서_한내~덕곡간(1) 4차로 확포장공사 사후환경영향조사용역(2019년분).pdf",
        "full_path": "Z:06010_환경\\1팀\\02.사후환경영향조사\\20190224ㅣ한내~덕곡간(1) 4차로 확포장공사 사후환경영향조사용역\\01 행정\\01 계약서\\2019년1차계약서\\20201015_(2019년1차)변경계약서_한내~덕곡간(1) 4차로 확포장공사 사후환경영향조사용역(2019년분).pdf",
        "depth": 3,
        "doc_type": "contract"
      }
    ],
    "specification": [
      {
        "type": "file",
        "name": "20191013417-00_1571017178302_과업지시서[한내_덕곡간(1) 4차로 확포장공사 사후환경영향조사용역].hwp",
        "path": "20191013417-00_1571017178302_과업지시서[한내_덕곡간(1) 4차로 확포장공사 사후환경영향조사용역].hwp",
        "full_path": "Z:06010_환경\\1팀\\02.사후환경영향조사\\20190224ㅣ한내~덕곡간(1) 4차로 확포장공사 사후환경영향조사용역\\01 행정\\20191013417-00_1571017178302_과업지시서[한내_덕곡간(1) 4차로 확포장공사 사후환경영향조사용역].hwp",
        "depth": 1,
        "doc_type": "specification"
      },
      {
        "type": "file",
        "name": "과업지시서[한내~덕곡(1) 사후-2024년].hwp",
        "path": "과업지시서[한내~덕곡(1) 사후-2024년].hwp",
        "full_path": "Z:06010_환경\\1팀\\02.사후환경영향조사\\20190224ㅣ한내~덕곡간(1) 4차로 확포장공사 사후환경영향조사용역\\01 행정\\08 설계변경\\5차년도 설계변경\\과업지시서[한내~덕곡(1) 사후-2024년].hwp",
        "depth": 3,
        "doc_type": "specification"
      },
      {
        "type": "file",
        "name": "@과업수행보고(차트).pdf",
        "path": "@과업수행보고(차트).pdf",
        "full_path": "Z:06010_환경\\1팀\\02.사후환경영향조사\\20190224ㅣ한내~덕곡간(1) 4차로 확포장공사 사후환경영향조사용역\\02 기술\\05 사후환경영향조사\\공사시 4차년도\\2분기\\@과업수행보고(차트).pdf",
        "depth": 4,
        "doc_type": "specification"
      }
    ],
    "initiation": [
      {
        "type": "file",
        "name": "02. 착수계(2021년분)-1set, 도로과,회계과제출용.pdf",
        "path": "02. 착수계(2021년분)-1set, 도로과,회계과제출용.pdf",
        "full_path": "Z:06010_환경\\1팀\\02.사후환경영향조사\\20190224ㅣ한내~덕곡간(1) 4차로 확포장공사 사후환경영향조사용역\\01 행정\\01 계약서\\2021년2차계약서\\02. 착수계(2021년분)-1set, 도로과,회계과제출용.pdf",
        "depth": 3,
        "doc_type": "initiation"
      },
      {
        "type": "file",
        "name": "착수계-한내덕곡.hwp",
        "path": "착수계-한내덕곡.hwp",
        "full_path": "Z:06010_환경\\1팀\\02.사후환경영향조사\\20190224ㅣ한내~덕곡간(1) 4차로 확포장공사 사후환경영향조사용역\\01 행정\\02 착수계\\1. 1차분\\1. 양식수령(한맥-수성)\\착수계-한내덕곡.hwp",
        "depth": 4,
        "doc_type": "initiation"
      },
      {
        "type": "file",
        "name": "착수계-한내덕곡_수성작성.hwp",
        "path": "착수계-한내덕곡_수성작성.hwp",
        "full_path": "Z:06010_환경\\1팀\\02.사후환경영향조사\\20190224ㅣ한내~덕곡간(1) 4차로 확포장공사 사후환경영향조사용역\\01 행정\\02 착수계\\1. 1차분\\2. 수성작성\\착수계-한내덕곡_수성작성.hwp",
        "depth": 4,
        "doc_type": "initiation"
      }
    ],
    "agreement": [
      {
        "type": "file",
        "name": "202401_협약서 결재용 보고자료.hwp",
        "path": "202401_협약서 결재용 보고자료.hwp",
        "full_path": "Z:06010_환경\\1팀\\02.사후환경영향조사\\20190224ㅣ한내~덕곡간(1) 4차로 확포장공사 사후환경영향조사용역\\01 행정\\03 업무분담합의\\01 1차\\202401_협약서 결재용 보고자료.hwp",
        "depth": 3,
        "doc_type": "agreement"
      },
      {
        "type": "file",
        "name": "(scan) 산학협정서 200110.pdf",
        "path": "(scan) 산학협정서 200110.pdf",
        "full_path": "Z:06010_환경\\1팀\\02.사후환경영향조사\\20190224ㅣ한내~덕곡간(1) 4차로 확포장공사 사후환경영향조사용역\\02 협력업체\\02측정대행계약\\(scan) 산학협정서 200110.pdf",
        "depth": 2,
        "doc_type": "agreement"
      },
      {
        "type": "file",
        "name": "산학협정서 200110.hwp",
        "path": "산학협정서 200110.hwp",
        "full_path": "Z:06010_환경\\1팀\\02.사후환경영향조사\\20190224ㅣ한내~덕곡간(1) 4차로 확포장공사 사후환경영향조사용역\\02 협력업체\\02측정대행계약\\산학협정서 200110.hwp",
        "depth": 2,
        "doc_type": "agreement"
      }
    ],
    "budget": [
      {
        "type": "file",
        "name": "(실행계획) 한내-덕곡(1) 도로 사후환경영향조사 용역.xlsx",
        "path": "(실행계획) 한내-덕곡(1) 도로 사후환경영향조사 용역.xlsx",
        "full_path": "Z:06010_환경\\1팀\\02.사후환경영향조사\\20190224ㅣ한내~덕곡간(1) 4차로 확포장공사 사후환경영향조사용역\\01 행정\\04 실행\\01 당초\\(실행계획) 한내-덕곡(1) 도로 사후환경영향조사 용역.xlsx",
        "depth": 3,
        "doc_type": "budget"
      },
      {
        "type": "file",
        "name": "(실행용)한내~덕곡 사후환경 설계예산서(통합본, 유리수정).xlsx",
        "path": "(실행용)한내~덕곡 사후환경 설계예산서(통합본, 유리수정).xlsx",
        "full_path": "Z:06010_환경\\1팀\\02.사후환경영향조사\\20190224ㅣ한내~덕곡간(1) 4차로 확포장공사 사후환경영향조사용역\\01 행정\\04 실행\\01 당초\\(실행용)한내~덕곡 사후환경 설계예산서(통합본, 유리수정).xlsx",
        "depth": 3,
        "doc_type": "budget"
      },
      {
        "type": "file",
        "name": "20200317_실행계획_한내-덕곡간 확포장도로 사후.pdf",
        "path": "20200317_실행계획_한내-덕곡간 확포장도로 사후.pdf",
        "full_path": "Z:06010_환경\\1팀\\02.사후환경영향조사\\20190224ㅣ한내~덕곡간(1) 4차로 확포장공사 사후환경영향조사용역\\01 행정\\04 실행\\01 당초\\20200317_실행계획_한내-덕곡간 확포장도로 사후.pdf",
        "depth": 3,
        "doc_type": "budget"
      }
    ],
    "deliverable1": [
      {
        "type": "file",
        "name": "@@성과품 사진 표지@@set(한내덕곡).hwp",
        "path": "@@성과품 사진 표지@@set(한내덕곡).hwp",
        "full_path": "Z:06010_환경\\1팀\\02.사후환경영향조사\\20190224ㅣ한내~덕곡간(1) 4차로 확포장공사 사후환경영향조사용역\\01 행정\\05 기성,준공\\2023년 4차(준공)\\@@성과품 사진 표지@@set(한내덕곡).hwp",
        "depth": 3,
        "doc_type": "deliverable1"
      },
      {
        "type": "file",
        "name": "한내-덕곡 사후환경 23년 2분기 보고서.zip",
        "path": "한내-덕곡 사후환경 23년 2분기 보고서.zip",
        "full_path": "Z:06010_환경\\1팀\\02.사후환경영향조사\\20190224ㅣ한내~덕곡간(1) 4차로 확포장공사 사후환경영향조사용역\\02 기술\\05 사후환경영향조사\\공사시 4차년도\\2분기\\한내-덕곡 사후환경 23년 2분기 보고서.zip",
        "depth": 4,
        "doc_type": "deliverable1"
      },
      {
        "type": "file",
        "name": "2023년 4분기 보고서 제출.pdf",
        "path": "2023년 4분기 보고서 제출.pdf",
        "full_path": "Z:06010_환경\\1팀\\02.사후환경영향조사\\20190224ㅣ한내~덕곡간(1) 4차로 확포장공사 사후환경영향조사용역\\02 기술\\05 사후환경영향조사\\공사시 5차년도\\1분기(23.12)\\2023년 4분기 보고서 제출.pdf",
        "depth": 4,
        "doc_type": "deliverable1"
      }
    ],
    "deliverable2": [
      {
        "type": "file",
        "name": "한내-덕곡 계획평면도.zip",
        "path": "한내-덕곡 계획평면도.zip",
        "full_path": "Z:06010_환경\\1팀\\02.사후환경영향조사\\20190224ㅣ한내~덕곡간(1) 4차로 확포장공사 사후환경영향조사용역\\02 기술\\03 관련자료\\계획평면도\\한내-덕곡 계획평면도.zip",
        "depth": 3,
        "doc_type": "deliverable2"
      },
      {
        "type": "file",
        "name": "동물탈출로 도면.pdf",
        "path": "동물탈출로 도면.pdf",
        "full_path": "Z:06010_환경\\1팀\\02.사후환경영향조사\\20190224ㅣ한내~덕곡간(1) 4차로 확포장공사 사후환경영향조사용역\\02 기술\\05 사후환경영향조사\\공사시 4차년도\\결과통보서\\수령자료-한맥\\첨부2. 수로탈출시설\\동물탈출로 도면.pdf",
        "depth": 6,
        "doc_type": "deliverable2"
      }
    ],
    "completion": [
      {
        "type": "file",
        "name": "2019년1차준공계 공문.pdf",
        "path": "2019년1차준공계 공문.pdf",
        "full_path": "Z:06010_환경\\1팀\\02.사후환경영향조사\\20190224ㅣ한내~덕곡간(1) 4차로 확포장공사 사후환경영향조사용역\\01 행정\\05 기성,준공\\2019년1차(준공)\\2019년1차준공계 공문.pdf",
        "depth": 3,
        "doc_type": "completion"
      },
      {
        "type": "file",
        "name": "2019년1차준공계_pdf.pdf",
        "path": "2019년1차준공계_pdf.pdf",
        "full_path": "Z:06010_환경\\1팀\\02.사후환경영향조사\\20190224ㅣ한내~덕곡간(1) 4차로 확포장공사 사후환경영향조사용역\\01 행정\\05 기성,준공\\2019년1차(준공)\\2019년1차준공계_pdf.pdf",
        "depth": 3,
        "doc_type": "completion"
      },
      {
        "type": "file",
        "name": "2021년분 준공계.pdf",
        "path": "2021년분 준공계.pdf",
        "full_path": "Z:06010_환경\\1팀\\02.사후환경영향조사\\20190224ㅣ한내~덕곡간(1) 4차로 확포장공사 사후환경영향조사용역\\01 행정\\05 기성,준공\\2021년 2차(준공)\\2021년분 준공계.pdf",
        "depth": 3,
        "doc_type": "completion"
      }
    ],
    "certificate": [
      {
        "type": "file",
        "name": "건설기술자 경력증명서_김기수 191101.pdf",
        "path": "건설기술자 경력증명서_김기수 191101.pdf",
        "full_path": "Z:06010_환경\\1팀\\02.사후환경영향조사\\20190224ㅣ한내~덕곡간(1) 4차로 확포장공사 사후환경영향조사용역\\01 행정\\02 착수계\\1. 1차분\\2. 수성작성\\건설기술자 경력증명서_김기수 191101.pdf",
        "depth": 4,
        "doc_type": "certificate"
      },
      {
        "type": "file",
        "name": "재직증명서_김기수 20191101.pdf",
        "path": "재직증명서_김기수 20191101.pdf",
        "full_path": "Z:06010_환경\\1팀\\02.사후환경영향조사\\20190224ㅣ한내~덕곡간(1) 4차로 확포장공사 사후환경영향조사용역\\01 행정\\02 착수계\\1. 1차분\\2. 수성작성\\재직증명서_김기수 20191101.pdf",
        "depth": 4,
        "doc_type": "certificate"
      },
      {
        "type": "file",
        "name": "경력증명서(김기수).pdf",
        "path": "경력증명서(김기수).pdf",
        "full_path": "Z:06010_환경\\1팀\\02.사후환경영향조사\\20190224ㅣ한내~덕곡간(1) 4차로 확포장공사 사후환경영향조사용역\\01 행정\\02 착수계\\2. 2차분\\경력증명서(김기수).pdf",
        "depth": 3,
        "doc_type": "certificate"
      }
    ]
  },
  "timestamp": "2025-03-08 13:56:47",
  "performance": {
    "total_time": 2.205782175064087,
    "search_time": 2.1867098808288574,
    "document_counts": {
      "contract": 3,
      "specification": 3,
      "initiation": 3,
      "agreement": 3,
      "budget": 3,
      "deliverable1": 3,
      "deliverable2": 2,
      "completion": 3,
      "certificate": 3
    }
  }
}