{
  "project_id": "20230002",
  "department_code": "10010",
  "department_name": "플랫폼사업실",
  "project_name": "A20230002_(3핵심)초연결 디지털 국토 실현을 위한 융복합 데이터의 통합 활용 및 운영 검증 체계 구축",
  "project_path": "Z:10010_플랫폼사업실\\A20230002_(3핵심)초연결 디지털 국토 실현을 위한 융복합 데이터의 통합 활용 및 운영 검증 체계 구축",
  "documents": {
    "agreement": [
      {
        "type": "file",
        "name": "2024년 협약서_초연결 디지털...3핵심(3차).pdf",
        "path": "2024년 협약서_초연결 디지털...3핵심(3차).pdf",
        "full_path": "Z:10010_플랫폼사업실\\A20230002_(3핵심)초연결 디지털 국토 실현을 위한 융복합 데이터의 통합 활용 및 운영 검증 체계 구축\\1. 과업 계약 및 착수\\1.01 계약\\1.01.03 계약서\\2024년 협약서_초연결 디지털...3핵심(3차).pdf",
        "depth": 3,
        "doc_type": "agreement"
      },
      {
        "type": "file",
        "name": "23-0210_국가연구개발사업 협약서(3핵심_2차년).pdf",
        "path": "23-0210_국가연구개발사업 협약서(3핵심_2차년).pdf",
        "full_path": "Z:10010_플랫폼사업실\\A20230002_(3핵심)초연결 디지털 국토 실현을 위한 융복합 데이터의 통합 활용 및 운영 검증 체계 구축\\1. 과업 계약 및 착수\\1.01 계약\\1.01.03 계약서\\23-0210_국가연구개발사업 협약서(3핵심_2차년).pdf",
        "depth": 3,
        "doc_type": "agreement"
      },
      {
        "type": "file",
        "name": "22-0425_국가연구개발사업 협약서.pdf",
        "path": "22-0425_국가연구개발사업 협약서.pdf",
        "full_path": "Z:10010_플랫폼사업실\\A20230002_(3핵심)초연결 디지털 국토 실현을 위한 융복합 데이터의 통합 활용 및 운영 검증 체계 구축\\1. 과업 계약 및 착수\\1.01 계약\\1.01.03 계약서\\22-0425_국가연구개발사업 협약서.pdf",
        "depth": 3,
        "doc_type": "agreement"
      }
    ],
    "deliverable1": [
      {
        "type": "file",
        "name": "실내외 공간 데이터 변환 기술 보고서_DC_SE_2_002-23-1016_ver5.hwp",
        "path": "실내외 공간 데이터 변환 기술 보고서_DC_SE_2_002-23-1016_ver5.hwp",
        "full_path": "Z:10010_플랫폼사업실\\A20230002_(3핵심)초연결 디지털 국토 실현을 위한 융복합 데이터의 통합 활용 및 운영 검증 체계 구축\\3. 성과품 작성\\3.02 보고서\\3.02.01 종합보고서\\실내외 공간 데이터 변환 기술 보고서_DC_SE_2_002-23-1016_ver5.hwp",
        "depth": 3,
        "doc_type": "deliverable1"
      },
      {
        "type": "file",
        "name": "비공간정보 위치정보 자동부여 기술 보고서_DC_SE_2_001-23-1017-ver3.hwp",
        "path": "비공간정보 위치정보 자동부여 기술 보고서_DC_SE_2_001-23-1017-ver3.hwp",
        "full_path": "Z:10010_플랫폼사업실\\A20230002_(3핵심)초연결 디지털 국토 실현을 위한 융복합 데이터의 통합 활용 및 운영 검증 체계 구축\\3. 성과품 작성\\3.02 보고서\\3.02.01 종합보고서\\비공간정보 위치정보 자동부여 기술 보고서_DC_SE_2_001-23-1017-ver3.hwp",
        "depth": 3,
        "doc_type": "deliverable1"
      }
    ]
  },
  "timestamp": "2025-03-10 03:12:55",
  "performance": {
    "total_time": 0.043746232986450195,
    "search_time": 0.025057315826416016,
    "document_counts": {
      "agreement": 3,
      "deliverable1": 2
    }
  }
}