{
  "project_id": "C20190088",
  "project_name": "백석천 비점오염 저감사업 기본 및 실시설계 용역",
  "department": "07010_상하수도부",
  "status": "준공",
  "contractor": "주관사",
  "documents": {
    "contract": {
      "exists": true,
      "details": [
        {
          "type": "file",
          "name": "02.내역서(백석천) 낙찰률적용-계약용.xls",
          "path": "02.내역서(백석천) 낙찰률적용-계약용.xls",
          "full_path": "Z:07010_상하수도\\Y2019088 백석천 비점오염저감사업 기본 및 실시설계\\01. 행정자료\\02. 계약서류\\02. 계약서\\02.내역서(백석천) 낙찰률적용-계약용.xls",
          "depth": 3,
          "doc_type": "contract"
        },
        {
          "type": "file",
          "name": "백석천 비점오염_계약서(최종).pdf",
          "path": "백석천 비점오염_계약서(최종).pdf",
          "full_path": "Z:07010_상하수도\\Y2019088 백석천 비점오염저감사업 기본 및 실시설계\\01. 행정자료\\02. 계약서류\\02. 계약서\\백석천 비점오염_계약서(최종).pdf",
          "depth": 3,
          "doc_type": "contract"
        },
        {
          "type": "file",
          "name": "계림_계약현황신고필증.pdf",
          "path": "계림_계약현황신고필증.pdf",
          "full_path": "Z:07010_상하수도\\Y2019088 백석천 비점오염저감사업 기본 및 실시설계\\01. 행정자료\\02. 계약서류\\04. 실적증명(CEMS)\\01.착수단계\\계림_계약현황신고필증.pdf",
          "depth": 4,
          "doc_type": "contract"
        }
      ]
    },
    "specification": {
      "exists": true,
      "details": [
        {
          "type": "file",
          "name": "20190401297-00_1554100309837_과업지시서(백석천).hwp",
          "path": "20190401297-00_1554100309837_과업지시서(백석천).hwp",
          "full_path": "Z:07010_상하수도\\Y2019088 백석천 비점오염저감사업 기본 및 실시설계\\01. 행정자료\\01. 과업수행계획\\01. 과업지시서\\20190401297-00_1554100309837_과업지시서(백석천).hwp",
          "depth": 3,
          "doc_type": "specification"
        },
        {
          "type": "file",
          "name": "증평과업수행계획서.hwp",
          "path": "증평과업수행계획서.hwp",
          "full_path": "Z:07010_상하수도\\Y2019088 백석천 비점오염저감사업 기본 및 실시설계\\01. 행정자료\\02. 계약서류\\03. 착수계\\01.작업\\증평과업수행계획서.hwp",
          "depth": 4,
          "doc_type": "specification"
        },
        {
          "type": "file",
          "name": "공문_과업중지요청.pdf",
          "path": "공문_과업중지요청.pdf",
          "full_path": "Z:07010_상하수도\\Y2019088 백석천 비점오염저감사업 기본 및 실시설계\\01. 행정자료\\04. 관련문서\\01. 발송공문\\[2020.04.02]_용역중지요청\\공문_과업중지요청.pdf",
          "depth": 4,
          "doc_type": "specification"
        }
      ]
    },
    "initiation": {
      "exists": true,
      "details": [
        {
          "type": "file",
          "name": "#1 세네카지(착수신고서).hwp",
          "path": "#1 세네카지(착수신고서).hwp",
          "full_path": "Z:07010_상하수도\\Y2019088 백석천 비점오염저감사업 기본 및 실시설계\\01. 행정자료\\02. 계약서류\\03. 착수계\\#1 세네카지(착수신고서).hwp",
          "depth": 3,
          "doc_type": "initiation"
        },
        {
          "type": "file",
          "name": "백석천 비점오염저감사업 착수신고서.hwp",
          "path": "백석천 비점오염저감사업 착수신고서.hwp",
          "full_path": "Z:07010_상하수도\\Y2019088 백석천 비점오염저감사업 기본 및 실시설계\\01. 행정자료\\02. 계약서류\\03. 착수계\\백석천 비점오염저감사업 착수신고서.hwp",
          "depth": 3,
          "doc_type": "initiation"
        },
        {
          "type": "file",
          "name": "백석천 비점오염저감사업 착수신고서_계림.hwp",
          "path": "백석천 비점오염저감사업 착수신고서_계림.hwp",
          "full_path": "Z:07010_상하수도\\Y2019088 백석천 비점오염저감사업 기본 및 실시설계\\01. 행정자료\\02. 계약서류\\03. 착수계\\01.작업\\백석천 비점오염저감사업 착수신고서_계림.hwp",
          "depth": 4,
          "doc_type": "initiation"
        }
      ]
    },
    "agreement": {
      "exists": true,
      "details": [
        {
          "type": "file",
          "name": "업무분담합의-백석천 비점오염.xlsx",
          "path": "업무분담합의-백석천 비점오염.xlsx",
          "full_path": "Z:07010_상하수도\\Y2019088 백석천 비점오염저감사업 기본 및 실시설계\\01. 행정자료\\03. 업무분담 및 실행\\01. 업무분담\\업무분담합의-백석천 비점오염.xlsx",
          "depth": 3,
          "doc_type": "agreement"
        },
        {
          "type": "file",
          "name": "붙임1_계약금액변경에 따른 업무분담금액(백석천).xlsx",
          "path": "붙임1_계약금액변경에 따른 업무분담금액(백석천).xlsx",
          "full_path": "Z:07010_상하수도\\Y2019088 백석천 비점오염저감사업 기본 및 실시설계\\01. 행정자료\\03. 업무분담 및 실행\\03. 업무분담(준공정산)\\붙임1_계약금액변경에 따른 업무분담금액(백석천).xlsx",
          "depth": 3,
          "doc_type": "agreement"
        },
        {
          "type": "file",
          "name": "업무분담(준공정산)_초안.zip",
          "path": "업무분담(준공정산)_초안.zip",
          "full_path": "Z:07010_상하수도\\Y2019088 백석천 비점오염저감사업 기본 및 실시설계\\01. 행정자료\\03. 업무분담 및 실행\\03. 업무분담(준공정산)\\업무분담(준공정산)_초안.zip",
          "depth": 3,
          "doc_type": "agreement"
        }
      ]
    },
    "budget": {
      "exists": true,
      "details": [
        {
          "type": "file",
          "name": "2019088_사업수행계획서및실행예산서(백석천 비점)rev0.xlsx",
          "path": "2019088_사업수행계획서및실행예산서(백석천 비점)rev0.xlsx",
          "full_path": "Z:07010_상하수도\\Y2019088 백석천 비점오염저감사업 기본 및 실시설계\\01. 행정자료\\03. 업무분담 및 실행\\02. 실행\\2019088_사업수행계획서및실행예산서(백석천 비점)rev0.xlsx",
          "depth": 3,
          "doc_type": "budget"
        },
        {
          "type": "file",
          "name": "백석천 비점오염저감사업 견적서(2019-05-22)-휴먼플래닛 실행가.pdf",
          "path": "백석천 비점오염저감사업 견적서(2019-05-22)-휴먼플래닛 실행가.pdf",
          "full_path": "Z:07010_상하수도\\Y2019088 백석천 비점오염저감사업 기본 및 실시설계\\01. 행정자료\\05. 기술지원(외주)\\01. 계약서\\03.견적서\\백석천 비점오염저감사업 견적서(2019-05-22)-휴먼플래닛 실행가.pdf",
          "depth": 4,
          "doc_type": "budget"
        },
        {
          "type": "file",
          "name": "백석천 비점오염저감사업 견적서(2019-07-08)-휴먼플래닛 실행가-최종.pdf",
          "path": "백석천 비점오염저감사업 견적서(2019-07-08)-휴먼플래닛 실행가-최종.pdf",
          "full_path": "Z:07010_상하수도\\Y2019088 백석천 비점오염저감사업 기본 및 실시설계\\01. 행정자료\\05. 기술지원(외주)\\01. 계약서\\03.견적서\\시뮬레이션\\백석천 비점오염저감사업 견적서(2019-07-08)-휴먼플래닛 실행가-최종.pdf",
          "depth": 5,
          "doc_type": "budget"
        }
      ]
    },
    "deliverable1": {
      "exists": true,
      "details": [
        {
          "type": "file",
          "name": "공문_월간(5,6월)공정보고서제출.pdf",
          "path": "공문_월간(5,6월)공정보고서제출.pdf",
          "full_path": "Z:07010_상하수도\\Y2019088 백석천 비점오염저감사업 기본 및 실시설계\\01. 행정자료\\04. 관련문서\\01. 발송공문\\[2019.07.11]_월간(5,6월)공정보고서제출\\공문_월간(5,6월)공정보고서제출.pdf",
          "depth": 4,
          "doc_type": "deliverable1"
        },
        {
          "type": "file",
          "name": "골지천유역 비점오염원 관리대책 마련 -최종보고서-.pdf",
          "path": "골지천유역 비점오염원 관리대책 마련 -최종보고서-.pdf",
          "full_path": "Z:07010_상하수도\\Y2019088 백석천 비점오염저감사업 기본 및 실시설계\\02. 설계자료\\01. 기초자료\\01.현황자료\\03.설계샘플자료\\골지천유역 비점오염원 관리대책 마련 -최종보고서-.pdf",
          "depth": 4,
          "doc_type": "deliverable1"
        },
        {
          "type": "file",
          "name": "골지천유역 비점오염관리대책 시행계획서_요약보고서.hwp",
          "path": "골지천유역 비점오염관리대책 시행계획서_요약보고서.hwp",
          "full_path": "Z:07010_상하수도\\Y2019088 백석천 비점오염저감사업 기본 및 실시설계\\02. 설계자료\\01. 기초자료\\01.현황자료\\03.설계샘플자료\\골지천 시행계획_최종_20171204_수성수자원\\골지천유역 비점오염관리대책 시행계획서_요약보고서.hwp",
          "depth": 5,
          "doc_type": "deliverable1"
        }
      ]
    },
    "deliverable2": {
      "exists": true,
      "details": [
        {
          "type": "file",
          "name": "유입관로 소구경추진공 도면.zip",
          "path": "유입관로 소구경추진공 도면.zip",
          "full_path": "Z:07010_상하수도\\Y2019088 백석천 비점오염저감사업 기본 및 실시설계\\02. 설계자료\\01. 기초자료\\01.현황자료\\03.설계샘플자료\\왕포천 생태하천 완료CD(14.04.18)_송현\\7. 유지용수토공사업비\\소구경추진공\\유입관로 소구경추진공 도면.zip",
          "depth": 7,
          "doc_type": "deliverable2"
        },
        {
          "type": "file",
          "name": "[붙임6] 샘플 도면 A3 (15.8Bx5.0H-3련).pdf",
          "path": "[붙임6] 샘플 도면 A3 (15.8Bx5.0H-3련).pdf",
          "full_path": "Z:07010_상하수도\\Y2019088 백석천 비점오염저감사업 기본 및 실시설계\\02. 설계자료\\01. 기초자료\\01.현황자료\\17.업체자료\\(주)우진산업_카다로그 및 신기술 자료\\1. 유압식 인양수문 (건설신기술 761호)\\[붙임6] 샘플 도면 A3 (15.8Bx5.0H-3련).pdf",
          "depth": 6,
          "doc_type": "deliverable2"
        },
        {
          "type": "file",
          "name": "[붙임5] 샘플 도면 (A3).pdf",
          "path": "[붙임5] 샘플 도면 (A3).pdf",
          "full_path": "Z:07010_상하수도\\Y2019088 백석천 비점오염저감사업 기본 및 실시설계\\02. 설계자료\\01. 기초자료\\01.현황자료\\17.업체자료\\(주)우진산업_카다로그 및 신기술 자료\\2. 유압식 전도수문 (방재신기술 제2016-6-3)\\[붙임5] 샘플 도면 (A3).pdf",
          "depth": 6,
          "doc_type": "deliverable2"
        }
      ]
    },
    "completion": {
      "exists": true,
      "details": [
        {
          "type": "file",
          "name": "백석천_준공계.zip",
          "path": "백석천_준공계.zip",
          "full_path": "Z:07010_상하수도\\Y2019088 백석천 비점오염저감사업 기본 및 실시설계\\01. 행정자료\\04. 관련문서\\05. 기타\\백석천_준공계.zip",
          "depth": 3,
          "doc_type": "completion"
        },
        {
          "type": "file",
          "name": "1.기성,준공 검사원_나무디엔씨.hwp",
          "path": "1.기성,준공 검사원_나무디엔씨.hwp",
          "full_path": "Z:07010_상하수도\\Y2019088 백석천 비점오염저감사업 기본 및 실시설계\\01. 행정자료\\05. 기술지원(외주)\\03. 선금 및 기성\\01.조경_나무디엔씨\\1.기성,준공 검사원_나무디엔씨.hwp",
          "depth": 4,
          "doc_type": "completion"
        },
        {
          "type": "file",
          "name": "01.준공금청구서_나무디엔씨.hwp",
          "path": "01.준공금청구서_나무디엔씨.hwp",
          "full_path": "Z:07010_상하수도\\Y2019088 백석천 비점오염저감사업 기본 및 실시설계\\01. 행정자료\\05. 기술지원(외주)\\04. 준공금\\01.조경_나무디엔씨\\01.준공금청구서_나무디엔씨.hwp",
          "depth": 4,
          "doc_type": "completion"
        }
      ]
    },
    "certificate": {
      "exists": true,
      "details": [
        {
          "type": "file",
          "name": "차영훈 건설기술자경력증명서.pdf",
          "path": "차영훈 건설기술자경력증명서.pdf",
          "full_path": "Z:07010_상하수도\\Y2019088 백석천 비점오염저감사업 기본 및 실시설계\\01. 행정자료\\02. 계약서류\\03. 착수계\\02.자격증,졸업증\\차영훈 건설기술자경력증명서.pdf",
          "depth": 4,
          "doc_type": "certificate"
        },
        {
          "type": "file",
          "name": "GNS코리아 폐업증명.pdf",
          "path": "GNS코리아 폐업증명.pdf",
          "full_path": "Z:07010_상하수도\\Y2019088 백석천 비점오염저감사업 기본 및 실시설계\\01. 행정자료\\05. 기술지원(외주)\\04. 준공금\\04.측량조사\\GNS코리아 폐업증명.pdf",
          "depth": 4,
          "doc_type": "certificate"
        }
      ]
    },
    "evaluation": {
      "exists": false,
      "details": []
    }
  },
  "project_path": "Z:07010_상하수도\\Y2019088 백석천 비점오염저감사업 기본 및 실시설계",
  "ai_analysis": "문서 분석 결과 (2025-03-08 13:54):\n## 프로젝트 C20190088 문서 분석 평가 결과\n\n**1. 현재 문서화 상태:** **중**\n\n**이유:** 본 프로젝트는 주관사이며 준공 상태임에도 불구하고,  `용역수행평가`가 누락되어 있습니다.  주관사 준공 프로젝트의 경우 모든 문서 유형이 100% 완비되어야 위험도 0/100을 달성합니다.  현재 모든 문서가 존재하지만, 용역수행평가의 누락으로 인해 완벽한 문서화 상태라고 볼 수 없습니다. 다른 문서들은 3개씩 존재하는 것으로 보아,  복수의 계약, 과업 등이 존재하여 관리상의 어려움이 있을 수 있으나, 본 평가에서는 문서 유형의 존재 여부에 초점을 맞추었습니다.\n\n\n**2. 가장 시급한 보완 필요 문서:** **용역수행평가**\n\n**이유:** 용역수행평가는 프로젝트의 전반적인 수행 과정과 결과에 대한 평가를 담고 있으며, 향후 유사 프로젝트 수행 시 중요한 참고 자료로 활용됩니다.  주관사 준공 프로젝트에서 이 문서가 누락된 것은 심각한 문제이며,  위험도를 높이는 주요 원인입니다.  또한,  준공 프로젝트의 완성도를 평가하는데 필수적인 요소입니다.\n\n\n**3. 위험도 점수 조정 필요성:** **있음**\n\n**구체적인 개선 방안:**\n\n* **즉시 용역수행평가를 작성하여 제출:**  프로젝트 담당자는  프로젝트의 전 과정을 분석하여 용역수행평가 보고서를 작성해야 합니다.  보고서에는 목표 달성 여부, 문제점 및 개선 사항,  성공 요인 등이 포함되어야 합니다.\n* **위험도 점수 조정:** 용역수행평가가 완료되면 위험도는 0/100으로 조정되어야 합니다. 현재 95/100의 위험도는 용역수행평가 미비로 인한 것이므로, 이 부분이 완료되면 위험도는 기준에 따라 0으로 수정되어야 합니다.\n* **문서 관리 체계 개선:**  계약서, 과업지시서 등 중요 문서들이 3개씩 존재하는 것은 관리상의 문제를 시사합니다. 문서 관리 체계를 개선하여 중복되는 문서를 통합하고,  버전 관리를 통해 최신 문서만 관리하도록 프로세스를 개선해야 합니다.  이는 향후 프로젝트의 위험도를 낮추는 데 중요한 역할을 합니다.\n\n\n결론적으로, 용역수행평가를 보완하고 문서 관리 체계를 개선하면 프로젝트 C20190088의 위험도를 크게 낮출 수 있습니다.\n\n\n요약:\n- 확인된 문서: 9개 유형\n- 누락된 문서: 1개 유형\n- 기본 위험도: 95/100\n",
  "timestamp": "2025-03-08 13:54:15",
  "performance": {
    "total_time": 0,
    "search_time": 9.764385461807251,
    "ai_time": 5.038408041000366,
    "save_time": 0
  }
}