{
  "project_id": "C20150076",
  "project_name": "밀양나노융합 국가산업단지 조사설계용역",
  "department": "04020_도시설계부",
  "status": "진행",
  "contractor": "비주관사",
  "documents": {
    "contract": {
      "exists": true,
      "details": [
        {
          "type": "file",
          "name": "나노 계약서.pdf",
          "path": "나노 계약서.pdf",
          "full_path": "Z:04020_도시설계\\2015076 밀양나노융합 국가산업단지 조사설계용역\\1. 과업 계약 및 착수\\1.01 계약\\1.01.03 계약서\\나노 계약서.pdf",
          "depth": 3,
          "doc_type": "contract"
        },
        {
          "type": "file",
          "name": "32-21-품의-11_[밀양나노] 기술지원 계약 요청.pdf",
          "path": "32-21-품의-11_[밀양나노] 기술지원 계약 요청.pdf",
          "full_path": "Z:04020_도시설계\\2015076 밀양나노융합 국가산업단지 조사설계용역\\1. 과업 계약 및 착수\\1.09 기술지원(외주)\\1.09.01 기술지원계약서\\32-21-품의-11_[밀양나노] 기술지원 계약 요청.pdf",
          "depth": 3,
          "doc_type": "contract"
        }
      ]
    },
    "specification": {
      "exists": true,
      "details": [
        {
          "type": "file",
          "name": "3. 밀양나노융합 국가산업단지 과업내용서(농업용수로).hwp",
          "path": "3. 밀양나노융합 국가산업단지 과업내용서(농업용수로).hwp",
          "full_path": "Z:04020_도시설계\\2015076 밀양나노융합 국가산업단지 조사설계용역\\1. 과업 계약 및 착수\\1.01 계약\\1.01.01 과업지시서\\3. 밀양나노융합 국가산업단지 과업내용서(농업용수로).hwp",
          "depth": 3,
          "doc_type": "specification"
        },
        {
          "type": "file",
          "name": "3. 밀양나노융합 국가산업단지 과업내용서(변경).hwp",
          "path": "3. 밀양나노융합 국가산업단지 과업내용서(변경).hwp",
          "full_path": "Z:04020_도시설계\\2015076 밀양나노융합 국가산업단지 조사설계용역\\1. 과업 계약 및 착수\\1.01 계약\\1.01.01 과업지시서\\3. 밀양나노융합 국가산업단지 과업내용서(변경).hwp",
          "depth": 3,
          "doc_type": "specification"
        },
        {
          "type": "file",
          "name": "3. 밀양나노융합 국가산업단지 과업내용서(농업용수로).hwp",
          "path": "3. 밀양나노융합 국가산업단지 과업내용서(농업용수로).hwp",
          "full_path": "Z:04020_도시설계\\2015076 밀양나노융합 국가산업단지 조사설계용역\\1. 과업 계약 및 착수\\1.09 기술지원(외주)\\1.09.02 과업지지서\\3. 밀양나노융합 국가산업단지 과업내용서(농업용수로).hwp",
          "depth": 3,
          "doc_type": "specification"
        }
      ]
    },
    "initiation": {
      "exists": true,
      "details": [
        {
          "type": "file",
          "name": "150526_밀양나노_착수계.pdf",
          "path": "150526_밀양나노_착수계.pdf",
          "full_path": "Z:04020_도시설계\\2015076 밀양나노융합 국가산업단지 조사설계용역\\1. 과업 계약 및 착수\\1.02 착수계\\1.02.03 착수계\\150526_밀양나노_착수계.pdf",
          "depth": 3,
          "doc_type": "initiation"
        }
      ]
    },
    "agreement": {
      "exists": true,
      "details": [
        {
          "type": "file",
          "name": "밀양나노협약서(2015.10).pdf",
          "path": "밀양나노협약서(2015.10).pdf",
          "full_path": "Z:04020_도시설계\\2015076 밀양나노융합 국가산업단지 조사설계용역\\1. 과업 계약 및 착수\\1.06 업무분담\\밀양나노협약서(2015.10).pdf",
          "depth": 2,
          "doc_type": "agreement"
        },
        {
          "type": "file",
          "name": "업무분담합의서(4차변경) 결재본 및 날인본(2015076 밀양나노융합 국가산업단지 조사설계용역).pdf",
          "path": "업무분담합의서(4차변경) 결재본 및 날인본(2015076 밀양나노융합 국가산업단지 조사설계용역).pdf",
          "full_path": "Z:04020_도시설계\\2015076 밀양나노융합 국가산업단지 조사설계용역\\1. 과업 계약 및 착수\\1.06 업무분담\\업무분담합의서(4차변경) 결재본 및 날인본(2015076 밀양나노융합 국가산업단지 조사설계용역).pdf",
          "depth": 2,
          "doc_type": "agreement"
        },
        {
          "type": "file",
          "name": "밀양나노 업무협약서(4차변경).pdf",
          "path": "밀양나노 업무협약서(4차변경).pdf",
          "full_path": "Z:04020_도시설계\\2015076 밀양나노융합 국가산업단지 조사설계용역\\1. 과업 계약 및 착수\\1.06 업무분담\\밀양나노 업무협약서(4차변경).pdf",
          "depth": 2,
          "doc_type": "agreement"
        }
      ]
    },
    "budget": {
      "exists": true,
      "details": [
        {
          "type": "file",
          "name": "밀양나노 실행예산서 변경03차.pdf",
          "path": "밀양나노 실행예산서 변경03차.pdf",
          "full_path": "Z:04020_도시설계\\2015076 밀양나노융합 국가산업단지 조사설계용역\\1. 과업 계약 및 착수\\1.06 업무분담\\밀양나노 실행예산서 변경03차.pdf",
          "depth": 2,
          "doc_type": "budget"
        },
        {
          "type": "file",
          "name": "밀양나노 실행예산서 변경03차.pdf",
          "path": "밀양나노 실행예산서 변경03차.pdf",
          "full_path": "Z:04020_도시설계\\2015076 밀양나노융합 국가산업단지 조사설계용역\\1. 과업 계약 및 착수\\1.07 실행\\밀양나노 실행예산서 변경03차.pdf",
          "depth": 2,
          "doc_type": "budget"
        },
        {
          "type": "file",
          "name": "밀양나노 실행예산(5차변경).pdf",
          "path": "밀양나노 실행예산(5차변경).pdf",
          "full_path": "Z:04020_도시설계\\2015076 밀양나노융합 국가산업단지 조사설계용역\\1. 과업 계약 및 착수\\1.07 실행\\밀양나노 실행예산(5차변경).pdf",
          "depth": 2,
          "doc_type": "budget"
        }
      ]
    },
    "deliverable1": {
      "exists": true,
      "details": [
        {
          "type": "file",
          "name": "000.보고서_세네카.hwp",
          "path": "000.보고서_세네카.hwp",
          "full_path": "Z:04020_도시설계\\2015076 밀양나노융합 국가산업단지 조사설계용역\\3. 성과품 작성\\3.02 보고서\\3.02.01 종합보고서\\000.보고서_세네카.hwp",
          "depth": 3,
          "doc_type": "deliverable1"
        },
        {
          "type": "file",
          "name": "000보고서_표지.hwp",
          "path": "000보고서_표지.hwp",
          "full_path": "Z:04020_도시설계\\2015076 밀양나노융합 국가산업단지 조사설계용역\\3. 성과품 작성\\3.02 보고서\\3.02.01 종합보고서\\000보고서_표지.hwp",
          "depth": 3,
          "doc_type": "deliverable1"
        },
        {
          "type": "file",
          "name": "제1편 제01장_사업의 개요.hwp",
          "path": "제1편 제01장_사업의 개요.hwp",
          "full_path": "Z:04020_도시설계\\2015076 밀양나노융합 국가산업단지 조사설계용역\\3. 성과품 작성\\3.02 보고서\\3.02.01 종합보고서\\제1편 제01장_사업의 개요.hwp",
          "depth": 3,
          "doc_type": "deliverable1"
        }
      ]
    },
    "deliverable2": {
      "exists": true,
      "details": [
        {
          "type": "file",
          "name": "도면목차 및 간지(밀양나노).dwg",
          "path": "도면목차 및 간지(밀양나노).dwg",
          "full_path": "Z:04020_도시설계\\2015076 밀양나노융합 국가산업단지 조사설계용역\\3. 성과품 작성\\3.01 설계도면\\3.01.01 설계도\\도면목차 및 간지(밀양나노).dwg",
          "depth": 3,
          "doc_type": "deliverable2"
        },
        {
          "type": "file",
          "name": "04_공사계획평면도(OK)_(현황 및 나노센터변경)(A1).dwg",
          "path": "04_공사계획평면도(OK)_(현황 및 나노센터변경)(A1).dwg",
          "full_path": "Z:04020_도시설계\\2015076 밀양나노융합 국가산업단지 조사설계용역\\3. 성과품 작성\\3.01 설계도면\\3.01.01 설계도\\1. 토공\\04_공사계획평면도(OK)_(현황 및 나노센터변경)(A1).dwg",
          "depth": 4,
          "doc_type": "deliverable2"
        },
        {
          "type": "file",
          "name": "05_정지계획평면도(A0).dwg",
          "path": "05_정지계획평면도(A0).dwg",
          "full_path": "Z:04020_도시설계\\2015076 밀양나노융합 국가산업단지 조사설계용역\\3. 성과품 작성\\3.01 설계도면\\3.01.01 설계도\\1. 토공\\05_정지계획평면도(A0).dwg",
          "depth": 4,
          "doc_type": "deliverable2"
        }
      ]
    },
    "completion": {
      "exists": false,
      "details": []
    },
    "certificate": {
      "exists": false,
      "details": []
    },
    "evaluation": {
      "exists": true,
      "details": [
        {
          "type": "file",
          "name": "(대표이사확인)1_용역수행협약서_201203(4차 변경)_관리용역1차.hwp",
          "path": "(대표이사확인)1_용역수행협약서_201203(4차 변경)_관리용역1차.hwp",
          "full_path": "Z:04020_도시설계\\2015076 밀양나노융합 국가산업단지 조사설계용역\\1. 과업 계약 및 착수\\1.06 업무분담\\(대표이사확인)1_용역수행협약서_201203(4차 변경)_관리용역1차.hwp",
          "depth": 2,
          "doc_type": "evaluation"
        },
        {
          "type": "file",
          "name": "20231207_용역수행협약서(5차변경)_re1.hwp",
          "path": "20231207_용역수행협약서(5차변경)_re1.hwp",
          "full_path": "Z:04020_도시설계\\2015076 밀양나노융합 국가산업단지 조사설계용역\\6. 관리용역\\협약변경\\20231207_용역수행협약서(5차변경)_re1.hwp",
          "depth": 2,
          "doc_type": "evaluation"
        },
        {
          "type": "file",
          "name": "20231213_용역수행협약서(5차변경)_re2.hwp",
          "path": "20231213_용역수행협약서(5차변경)_re2.hwp",
          "full_path": "Z:04020_도시설계\\2015076 밀양나노융합 국가산업단지 조사설계용역\\6. 관리용역\\협약변경\\20231213_용역수행협약서(5차변경)_re2.hwp",
          "depth": 2,
          "doc_type": "evaluation"
        }
      ]
    }
  },
  "project_path": "Z:04020_도시설계\\2015076 밀양나노융합 국가산업단지 조사설계용역",
  "ai_analysis": "문서 분석 결과 (2025-03-10 01:34):\n## 프로젝트 C20150076 문서 분석 결과\n\n**1. 현재 문서화 상태:** 중\n\n**이유:**  비주관사로서 필수 문서인 계약서, 공동도급협정, 성과품(보고서/도면)은 모두 확보되어 있습니다. 하지만,  진행 중인 프로젝트임을 감안하더라도  과업지시서, 착수계, 실행예산 외  준공계와 실적증명이 누락되어 있습니다.  비주관사 기준 위험도 50/100 이하를 만족하지만, 프로젝트 완료를 위해 필요한 문서가 부족하여 '중'으로 평가합니다.  완료 후 준공계와 실적증명이 없다면 심각한 문제가 발생할 수 있습니다.\n\n**2. 가장 시급한 보완 필요 문서:** 준공계, 실적증명\n\n**이유:**  이 두 문서는 프로젝트 완료를 공식적으로 증명하는 필수 문서입니다.  현재 프로젝트가 진행 중이지만,  준공 시점에 이 문서들이 없으면 프로젝트 종료 및 대금 지급에 차질이 발생할 수 있습니다. 따라서 즉시 준비하여 보완해야 합니다.\n\n**3. 위험도 점수 조정 필요성:** 있음\n\n**구체적인 개선 방안:**\n\n현재 위험도 100/100은  주관사 기준으로 평가한 결과로 보이며, 비주관사인 본 프로젝트에는 적절하지 않습니다.  준공계와 실적증명을 확보하는 것을 전제로, 위험도를 조정합니다.\n\n* **위험도 조정 후 점수:** 60/100\n\n* **조정 이유:**  필수 문서는 확보되었으나, 프로젝트 완료에 필수적인 준공계와 실적증명이 누락되어 있고, 진행 중인 프로젝트의 특성상 향후 발생 가능한 위험을 고려하여 60/100으로 조정합니다. 준공계와 실적증명이 확보되면 위험도는 30/100 수준으로 낮아질 수 있습니다.\n\n* **추가 개선 방안:**\n    * 프로젝트 진행 상황을 정기적으로 기록하고 관리하는 시스템을 구축하여 향후 문서 누락을 방지합니다.\n    *  준공계 및 실적증명 작성에 필요한 정보들을 미리 수집하고 체크리스트를 활용하여 누락 없이 준비합니다.\n    *  담당자에게 문서 관리에 대한 교육을 실시합니다.\n\n\n위와 같이 문서 관리 체계를 개선하여 향후 프로젝트의 위험도를 줄이는 데 집중해야 합니다.\n\n\n요약:\n- 확인된 문서: 8개 유형\n- 누락된 문서: 2개 유형\n- 기본 위험도: 100/100\n",
  "timestamp": "2025-03-10 01:34:00",
  "performance": {
    "total_time": 0,
    "search_time": 6.689588308334351,
    "ai_time": 4.8712780475616455,
    "save_time": 0
  }
}